pyirishrail/__init__.py
pyirishrail/pyirishrail.py
pyirishrail-0.0.1.dist-info/DESCRIPTION.rst
pyirishrail-0.0.1.dist-info/METADATA
pyirishrail-0.0.1.dist-info/RECORD
pyirishrail-0.0.1.dist-info/WHEEL
pyirishrail-0.0.1.dist-info/metadata.json
pyirishrail-0.0.1.dist-info/top_level.txt
