Metadata-Version: 2.0
Name: pyirishrail
Version: 0.0.1
Summary: Python library to get the real-time transport information (RTPI) from Irish Rail
Home-page: https://github.com/ttroy50/pyirishrail
Author: Thom Troy
Author-email: ttroy50@gmail.com
License: MIT
Download-URL: https://github.com/ttroy50/pyirishrail/archive/0.0.1.tar.gz
Keywords: irish rail RTPI
Platform: any
Requires-Dist: requests
